kinase_library/__init__.py
kinase_library/logger.py
kinase_library/databases/kinase_data/base_tree.svg
kinase_library/databases/kinase_data/kinome_information.tsv
kinase_library/databases/matrices/ser_thr/ser_thr_all_log2_matrices.tsv
kinase_library/databases/matrices/ser_thr/ser_thr_all_norm_matrices.tsv
kinase_library/databases/matrices/ser_thr/ser_thr_all_raw_matrices.tsv
kinase_library/databases/matrices/ser_thr/st_favorability.tsv
kinase_library/databases/matrices/ser_thr/densitometry/AAK1_densitometry.txt
kinase_library/databases/matrices/ser_thr/densitometry/ACVR2A_densitometry.txt
kinase_library/databases/matrices/ser_thr/densitometry/ACVR2B_densitometry.txt
kinase_library/databases/matrices/ser_thr/densitometry/AKT1_densitometry.txt
kinase_library/databases/matrices/ser_thr/densitometry/AKT2_densitometry.txt
kinase_library/databases/matrices/ser_thr/densitometry/AKT3_densitometry.txt
kinase_library/databases/matrices/ser_thr/densitometry/ALK1_densitometry.txt
kinase_library/databases/matrices/ser_thr/densitometry/ALK2_densitometry.txt
kinase_library/databases/matrices/ser_thr/densitometry/ALK4_densitometry.txt
kinase_library/databases/matrices/ser_thr/densitometry/ALK7_densitometry.txt
kinase_library/databases/matrices/ser_thr/densitometry/ALPHAK3_densitometry.txt
kinase_library/databases/matrices/ser_thr/densitometry/AMPKA1_densitometry.txt
kinase_library/databases/matrices/ser_thr/densitometry/AMPKA2_densitometry.txt
kinase_library/databases/matrices/ser_thr/densitometry/ANKRD3_densitometry.txt
kinase_library/databases/matrices/ser_thr/densitometry/ASK1_densitometry.txt
kinase_library/databases/matrices/ser_thr/densitometry/ATM_densitometry.txt
kinase_library/databases/matrices/ser_thr/densitometry/ATR_densitometry.txt
kinase_library/databases/matrices/ser_thr/densitometry/AURA_densitometry.txt
kinase_library/databases/matrices/ser_thr/densitometry/AURB_densitometry.txt
kinase_library/databases/matrices/ser_thr/densitometry/AURC_densitometry.txt
kinase_library-1.5.1.dist-info/licenses/LICENSE
kinase_library-1.5.1.dist-info/METADATA
kinase_library-1.5.1.dist-info/WHEEL
kinase_library-1.5.1.dist-info/top_level.txt
kinase_library-1.5.1.dist-info/RECORD
