Metadata-Version: 2.4
Name: kinase-library
Version: 1.5.1
Summary: The Kinase Library Project: a Global Atlas of the Human Protein Kinome
Author-email: yaront <tmy2110@cumc.columbia.edu>, harinlee0803 <harin.lee@cellsignal.com>, sean-landry <sean.landry@cellsignal.com>
License: Creative Commons Attribution-NonCommercial-ShareAlike 3.0 Unported
Project-URL: Homepage, https://kinase-library.phosphosite.org
Project-URL: Source, https://github.com/TheKinaseLibrary/kinase-library
Project-URL: Documentation, https://kinase-library.readthedocs.io
Keywords: kinase,phosphorylation,substrate,motif,substrate specificity,cell signaling,signaling,phosphoproteomics,kinase enrichment,signaling network,kinome,peptide library,phosphosite
Requires-Python: <=3.13,>=3.10
License-File: LICENSE
Requires-Dist: adjustText~=1.3.0
Requires-Dist: Bio~=1.7.1
Requires-Dist: biopython~=1.81
Requires-Dist: gseapy~=1.1.8
Requires-Dist: matplotlib~=3.8.3
Requires-Dist: natsort~=8.3.1
Requires-Dist: numpy~=1.26.4
Requires-Dist: pandas~=2.2.3
Requires-Dist: pyarrow~=18.0.0
Requires-Dist: scikit_learn~=1.6.0
Requires-Dist: scipy~=1.14.1
Requires-Dist: seaborn~=0.13.2
Requires-Dist: statsmodels~=0.14.2
Requires-Dist: tqdm~=4.66.5
Requires-Dist: sphinx-autodoc-typehints~=2.5.0
Requires-Dist: sphinx-rtd-theme~=3.0.2
Requires-Dist: nbsphinx~=0.9.5
Requires-Dist: myst-parser~=4.0.0
Requires-Dist: openpyxl~=3.1.5
Dynamic: license-file
